thawani/__init__.py
thawani/client.py
thawani/errors.py
thawani/constants/__init__.py
thawani/constants/error_code.py
thawani/constants/http_status_code.py
thawani/constants/url.py
thawani/resources/__init__.py
thawani/resources/addon.py
thawani/resources/base.py
thawani/resources/card.py
thawani/resources/checkout.py
thawani/resources/customer.py
thawani/resources/fund_account.py
thawani/resources/invoice.py
thawani/resources/item.py
thawani/resources/order.py
thawani/resources/payment.py
thawani/resources/payment_intent.py
thawani/resources/payment_link.py
thawani/resources/payment_method.py
thawani/resources/plan.py
thawani/resources/qrcode.py
thawani/resources/refund.py
thawani/resources/registration_link.py
thawani/resources/settlement.py
thawani/resources/subscription.py
thawani/resources/token.py
thawani/resources/transfer.py
thawani/resources/virtual_account.py
thawani/utility/__init__.py
thawani/utility/utility.py
thawani-1.1.2.dist-info/LICENSE
thawani-1.1.2.dist-info/METADATA
thawani-1.1.2.dist-info/WHEEL
thawani-1.1.2.dist-info/top_level.txt
thawani-1.1.2.dist-info/RECORD
