Metadata-Version: 2.1
Name: thawani
Version: 1.1.2
Summary: Thawani Python Client
Home-page: https://github.com/muradlansa/thawani-python
Author: Murad Lansa
Author-email: mail@muradlansa.com
License: MIT
Keywords: Thawani Payment gateway Oman
License-File: LICENSE
Requires-Dist: requests
